coupledmodeldriver/__init__.py
coupledmodeldriver/_depend.py
coupledmodeldriver/client/__init__.py
coupledmodeldriver/client/check_completion.py
coupledmodeldriver/client/generate_adcirc.py
coupledmodeldriver/client/generate_schism.py
coupledmodeldriver/client/initialize_adcirc.py
coupledmodeldriver/client/initialize_schism.py
coupledmodeldriver/client/unqueued_runs.py
coupledmodeldriver/configure/__init__.py
coupledmodeldriver/configure/base.py
coupledmodeldriver/configure/configure.py
coupledmodeldriver/configure/forcings/__init__.py
coupledmodeldriver/configure/forcings/base.py
coupledmodeldriver/configure/models.py
coupledmodeldriver/generate/__init__.py
coupledmodeldriver/generate/adcirc/__init__.py
coupledmodeldriver/generate/adcirc/base.py
coupledmodeldriver/generate/adcirc/check.py
coupledmodeldriver/generate/adcirc/configure.py
coupledmodeldriver/generate/adcirc/generate.py
coupledmodeldriver/generate/adcirc/script.py
coupledmodeldriver/generate/schism/__init__.py
coupledmodeldriver/generate/schism/base.py
coupledmodeldriver/generate/schism/check.py
coupledmodeldriver/generate/schism/configure.py
coupledmodeldriver/generate/schism/generate.py
coupledmodeldriver/generate/schism/script.py
coupledmodeldriver/platforms.py
coupledmodeldriver/script.py
coupledmodeldriver/utilities.py
coupledmodeldriver-1.7.1.post1.dist-info/entry_points.txt
coupledmodeldriver-1.7.1.post1.dist-info/LICENSE
coupledmodeldriver-1.7.1.post1.dist-info/WHEEL
coupledmodeldriver-1.7.1.post1.dist-info/METADATA
coupledmodeldriver-1.7.1.post1.dist-info/RECORD
