Metadata-Version: 2.1
Name: coupledmodeldriver
Version: 1.7.1.post1
Summary: coupled model configuration generation
Home-page: https://github.com/noaa-ocs-modeling/CoupledModelDriver.git
License: CC0-1.0
Author: Zach Burnett
Author-email: zachary.r.burnett@gmail.com
Requires-Python: >=3.8,<3.12
Classifier: License :: CC0 1.0 Universal (CC0 1.0) Public Domain Dedication
Classifier: Programming Language :: Python :: 3
Classifier: Programming Language :: Python :: 3.8
Classifier: Programming Language :: Python :: 3.9
Classifier: Programming Language :: Python :: 3.10
Classifier: Programming Language :: Python :: 3.11
Provides-Extra: adcirc
Provides-Extra: development
Provides-Extra: documentation
Provides-Extra: testing
Requires-Dist: adcircpy (>=1.3); extra == "adcirc"
Requires-Dist: dunamai; extra == "documentation"
Requires-Dist: file-read-backwards
Requires-Dist: fiona
Requires-Dist: isort; extra == "development"
Requires-Dist: m2r2; extra == "documentation"
Requires-Dist: nemspy (>=1.0.4)
Requires-Dist: numpy
Requires-Dist: oitnb; extra == "development"
Requires-Dist: pooch; extra == "testing"
Requires-Dist: pyproj
Requires-Dist: pyschism (>0.1.13)
Requires-Dist: pytest-cov; extra == "testing"
Requires-Dist: pytest-socket; extra == "testing"
Requires-Dist: pytest-xdist; extra == "testing"
Requires-Dist: pytest; extra == "testing"
Requires-Dist: sphinx-rtd-theme; extra == "documentation"
Requires-Dist: sphinx; extra == "documentation"
Requires-Dist: sphinxcontrib-programoutput; extra == "documentation"
Requires-Dist: stormevents (>=2.2.5,!=2.3.0,!=2.3.1)
Requires-Dist: typepigeon (>=1.0.3,<2.0.0)
Project-URL: Documentation, https://coupledmodeldriver.readthedocs.io
Project-URL: Repository, https://github.com/noaa-ocs-modeling/CoupledModelDriver.git
